{
  "scriptId": "34",
  "url": "internal:ext/fetch/23_request.js",
  "functions": [
    {
      "functionName": "processUrlList",
      "ranges": [
        { "startOffset": 1938, "endOffset": 2175, "count": 1 },
        { "startOffset": 2083, "endOffset": 2136, "count": 0 }
      ],
      "isBlockCoverage": true
    },
    {
      "functionName": "newInnerRequest",
      "ranges": [
        { "startOffset": 3039, "endOffset": 4961, "count": 1 },
        { "startOffset": 3210, "endOffset": 3262, "count": 0 },
        { "startOffset": 4163, "endOffset": 4168, "count": 0 }
      ],
      "isBlockCoverage": true
    },
    {
      "functionName": "get method",
      "ranges": [
        { "startOffset": 3307, "endOffset": 3573, "count": 4 },
        { "startOffset": 3361, "endOffset": 3532, "count": 0 }
      ],
      "isBlockCoverage": true
    },
    {
      "functionName": "set method",
      "ranges": [{ "startOffset": 3581, "endOffset": 3642, "count": 1 }],
      "isBlockCoverage": true
    },
    {
      "functionName": "get headerList",
      "ranges": [
        { "startOffset": 3679, "endOffset": 3966, "count": 4 },
        { "startOffset": 3741, "endOffset": 3921, "count": 1 },
        { "startOffset": 3820, "endOffset": 3911, "count": 0 }
      ],
      "isBlockCoverage": true
    },
    {
      "functionName": "set headerList",
      "ranges": [{ "startOffset": 3974, "endOffset": 4043, "count": 0 }],
      "isBlockCoverage": false
    },
    {
      "functionName": "urlList",
      "ranges": [{ "startOffset": 4153, "endOffset": 4162, "count": 1 }],
      "isBlockCoverage": true
    },
    {
      "functionName": "url",
      "ranges": [{ "startOffset": 4248, "endOffset": 4542, "count": 0 }],
      "isBlockCoverage": false
    },
    {
      "functionName": "currentUrl",
      "ranges": [
        { "startOffset": 4550, "endOffset": 4949, "count": 1 },
        { "startOffset": 4792, "endOffset": 4879, "count": 0 }
      ],
      "isBlockCoverage": true
    },
    {
      "functionName": "isKnownMethod",
      "ranges": [
        { "startOffset": 6842, "endOffset": 7025, "count": 1 },
        { "startOffset": 6925, "endOffset": 6946, "count": 0 },
        { "startOffset": 6947, "endOffset": 6971, "count": 0 },
        { "startOffset": 6972, "endOffset": 6993, "count": 0 },
        { "startOffset": 6994, "endOffset": 7014, "count": 0 }
      ],
      "isBlockCoverage": true
    },
    {
      "functionName": "validateAndNormalizeMethod",
      "ranges": [
        { "startOffset": 7086, "endOffset": 7575, "count": 1 },
        { "startOffset": 7216, "endOffset": 7459, "count": 0 },
        { "startOffset": 7460, "endOffset": 7484, "count": 0 },
        { "startOffset": 7491, "endOffset": 7574, "count": 0 }
      ],
      "isBlockCoverage": true
    },
    {
      "functionName": "<instance_members_initializer>",
      "ranges": [{ "startOffset": 7579, "endOffset": 14952, "count": 1 }],
      "isBlockCoverage": false
    },
    {
      "functionName": "",
      "ranges": [
        { "startOffset": 7742, "endOffset": 7906, "count": 7 },
        { "startOffset": 7806, "endOffset": 7866, "count": 0 }
      ],
      "isBlockCoverage": true
    },
    {
      "functionName": "",
      "ranges": [{ "startOffset": 7912, "endOffset": 7976, "count": 1 }],
      "isBlockCoverage": true
    },
    {
      "functionName": "",
      "ranges": [{ "startOffset": 8028, "endOffset": 8214, "count": 0 }],
      "isBlockCoverage": false
    },
    {
      "functionName": "",
      "ranges": [{ "startOffset": 8219, "endOffset": 8359, "count": 0 }],
      "isBlockCoverage": false
    },
    {
      "functionName": "Request",
      "ranges": [
        { "startOffset": 8498, "endOffset": 12694, "count": 1 },
        { "startOffset": 9315, "endOffset": 9723, "count": 0 },
        { "startOffset": 9842, "endOffset": 9897, "count": 0 },
        { "startOffset": 10130, "endOffset": 10169, "count": 0 },
        { "startOffset": 10286, "endOffset": 10663, "count": 0 },
        { "startOffset": 10812, "endOffset": 10872, "count": 0 },
        { "startOffset": 11231, "endOffset": 11276, "count": 0 },
        { "startOffset": 11597, "endOffset": 11640, "count": 0 },
        { "startOffset": 11700, "endOffset": 11728, "count": 0 },
        { "startOffset": 11767, "endOffset": 11788, "count": 0 },
        { "startOffset": 11831, "endOffset": 11919, "count": 0 },
        { "startOffset": 12009, "endOffset": 12030, "count": 0 },
        { "startOffset": 12032, "endOffset": 12269, "count": 0 },
        { "startOffset": 12455, "endOffset": 12642, "count": 0 }
      ],
      "isBlockCoverage": true
    },
    {
      "functionName": "",
      "ranges": [{ "startOffset": 9206, "endOffset": 9217, "count": 0 }],
      "isBlockCoverage": false
    },
    {
      "functionName": "",
      "ranges": [{ "startOffset": 9255, "endOffset": 9263, "count": 1 }],
      "isBlockCoverage": true
    },
    {
      "functionName": "get method",
      "ranges": [
        { "startOffset": 12700, "endOffset": 13042, "count": 2 },
        { "startOffset": 12792, "endOffset": 12944, "count": 1 },
        { "startOffset": 12944, "endOffset": 13036, "count": 0 }
      ],
      "isBlockCoverage": true
    },
    {
      "functionName": "get url",
      "ranges": [
        { "startOffset": 13048, "endOffset": 13366, "count": 2 },
        { "startOffset": 13134, "endOffset": 13275, "count": 1 },
        { "startOffset": 13275, "endOffset": 13360, "count": 0 }
      ],
      "isBlockCoverage": true
    },
    {
      "functionName": "get headers",
      "ranges": [{ "startOffset": 13372, "endOffset": 13474, "count": 2 }],
      "isBlockCoverage": true
    },
    {
      "functionName": "get redirect",
      "ranges": [{ "startOffset": 13480, "endOffset": 13672, "count": 0 }],
      "isBlockCoverage": false
    },
    {
      "functionName": "get signal",
      "ranges": [{ "startOffset": 13678, "endOffset": 13778, "count": 4 }],
      "isBlockCoverage": true
    },
    {
      "functionName": "clone",
      "ranges": [{ "startOffset": 13784, "endOffset": 14592, "count": 0 }],
      "isBlockCoverage": false
    },
    {
      "functionName": "",
      "ranges": [{ "startOffset": 14598, "endOffset": 14948, "count": 0 }],
      "isBlockCoverage": false
    },
    {
      "functionName": "webidl.converters.RequestInfo_DOMString",
      "ranges": [
        { "startOffset": 15243, "endOffset": 15595, "count": 1 },
        { "startOffset": 15328, "endOffset": 15460, "count": 0 }
      ],
      "isBlockCoverage": true
    },
    {
      "functionName": "toInnerRequest",
      "ranges": [{ "startOffset": 16508, "endOffset": 16576, "count": 1 }],
      "isBlockCoverage": true
    },
    {
      "functionName": "fromFlashRequest",
      "ranges": [
        { "startOffset": 17469, "endOffset": 17967, "count": 1 },
        { "startOffset": 17682, "endOffset": 17703, "count": 0 }
      ],
      "isBlockCoverage": true
    },
    {
      "functionName": "request.<computed>",
      "ranges": [{ "startOffset": 17891, "endOffset": 17942, "count": 0 }],
      "isBlockCoverage": false
    }
  ]
}
